snap2txt/.il
snap2txt/.wl
snap2txt/__init__.py
snap2txt/__main__.py
snap2txt/saver.py
snap2txt-0.2.0.dist-info/LICENSE
snap2txt-0.2.0.dist-info/METADATA
snap2txt-0.2.0.dist-info/WHEEL
snap2txt-0.2.0.dist-info/entry_points.txt
snap2txt-0.2.0.dist-info/top_level.txt
snap2txt-0.2.0.dist-info/RECORD
