Metadata-Version: 2.2
Name: snap2txt
Version: 0.2.0
Summary: A tool to save project structure and contents to a text file
Home-page: https://github.com/vorniches/snap2txt
Author: Sergei Vorniches
Author-email: vorniches@gmail.com
License: MIT
Classifier: Programming Language :: Python :: 3
Classifier: License :: OSI Approved :: MIT License
Classifier: Operating System :: OS Independent
Requires-Python: >=3.6
License-File: LICENSE
Dynamic: author
Dynamic: author-email
Dynamic: classifier
Dynamic: description
Dynamic: description-content-type
Dynamic: home-page
Dynamic: license
Dynamic: requires-python
Dynamic: summary
